hdata/__init__.py
hdata/force_validation.py
hdata/functions.py
hdata/models.py
hdata-0.17.0.dist-info/METADATA
hdata-0.17.0.dist-info/WHEEL
hdata-0.17.0.dist-info/RECORD
